hyperdim/__init__.py
hyperdim/encoders.py
hyperdim/hdmodel.py
hyperdim/kernels.py
hyperdim/utils.py
hyperdim-0.0.6.dist-info/METADATA
hyperdim-0.0.6.dist-info/WHEEL
hyperdim-0.0.6.dist-info/top_level.txt
hyperdim-0.0.6.dist-info/RECORD
