Metadata-Version: 2.1
Name: hyperdim
Version: 0.0.6
Summary: Hyperdimensionality computing machine learning library
Home-page: https://gitlab.com/da_doomer/hyperdim
License: UNKNOWN
Platform: UNKNOWN
Classifier: Programming Language :: Python :: 3
Classifier: License :: OSI Approved :: MIT License
Classifier: Operating System :: OS Independent
Requires-Python: >=3.6
Requires-Dist: tqdm
Requires-Dist: numpy
Requires-Dist: sklearn
